odoo/addons/femprocomuns/__init__.py
odoo/addons/femprocomuns/__manifest__.py
odoo/addons/femprocomuns/controllers/__init__.py
odoo/addons/femprocomuns/controllers/website_subscription.py
odoo/addons/femprocomuns/models/__init__.py
odoo/addons/femprocomuns/models/subscription_request.py
odoo/addons/femprocomuns/views/subscription_request_view.xml
odoo/addons/femprocomuns/views/subscription_template.xml
odoo14_addon_femprocomuns-14.0.0.0.0.dist-info/METADATA
odoo14_addon_femprocomuns-14.0.0.0.0.dist-info/WHEEL
odoo14_addon_femprocomuns-14.0.0.0.0.dist-info/top_level.txt
odoo14_addon_femprocomuns-14.0.0.0.0.dist-info/RECORD
